qwark/__init__.abi3.so
qwark/_version.abi3.so
qwark/ark.abi3.so
qwark/pipu.abi3.so
qwark/arkits/__init__.abi3.so
qwark/arkits/basics.abi3.so
qwark/arkits/frame.abi3.so
qwark/arkits/logger.abi3.so
qwark/arkits/qtside.abi3.so
qwark/arkits/qtweb.abi3.so
qwark/arkits/theme.abi3.so
qwark/canvas/__init__.abi3.so
qwark/canvas/colors.abi3.so
qwark/canvas/flowstep.abi3.so
qwark/canvas/glcanvas.abi3.so
qwark/canvas/mpcanvas.abi3.so
qwark/canvas/qtcanvas.abi3.so
qwark/canvas/quarkplot.abi3.so
qwark/editor/__init__.abi3.so
qwark/editor/editor.abi3.so
qwark/editor/lexer.abi3.so
qwark/explorer/__init__.abi3.so
qwark/explorer/explorer.abi3.so
qwark/explorer/registry.abi3.so
qwark/explorer/sysinfo.abi3.so
qwark/explorer/tree.abi3.so
"qwark/uicon/Inter-VariableFont_opsz,wght.ttf"
"qwark/uicon/MaterialSymbolsOutlined[FILL,GRAD,opsz,wght].ttf"
qwark/uicon/__init__.py
qwark/uicon/style.qss
qwark/utility/__init__.abi3.so
qwark/utility/console.abi3.so
qwark/utility/nbserver.abi3.so
qwark-1.2.6.dist-info/licenses/project/LICENSE
qwark-1.2.6.dist-info/METADATA
qwark-1.2.6.dist-info/WHEEL
qwark-1.2.6.dist-info/top_level.txt
qwark-1.2.6.dist-info/RECORD
