Metadata-Version: 2.4
Name: qwark
Version: 1.2.6
Summary: project description
Author-email: YL <fengyulong@pku.org.cn>
License-Expression: MIT
Project-URL: homepage, https://gitee.com
Project-URL: documentation, https://gitee.com
Project-URL: bugs, https://gitee.com
Classifier: Development Status :: 5 - Production/Stable
Classifier: Intended Audience :: Developers
Classifier: Intended Audience :: Science/Research
Classifier: Natural Language :: Chinese (Simplified)
Classifier: Natural Language :: English
Classifier: Operating System :: Microsoft :: Windows
Classifier: Operating System :: POSIX :: Linux
Classifier: Operating System :: MacOS :: MacOS X
Classifier: Programming Language :: Python :: 3.12
Classifier: Topic :: Scientific/Engineering :: Physics
Requires-Python: >=3.12
License-File: project/LICENSE
Requires-Dist: pyside6>=6.4.2
Requires-Dist: pyqtgraph>=0.12.4
Requires-Dist: matplotlib>=3.6.3
Requires-Dist: vispy>=0.12.0
Requires-Dist: qtconsole>=0.12.0
Requires-Dist: srpc>=4.2.8
Requires-Dist: zee>=0.0.2
Requires-Dist: jedi
Requires-Dist: h5py
Dynamic: license-file
